{
    "title": "",
    "id": "evening_3",
    "questions": [
        {
            "id": "effort_investment",
            "questionText": "Ich habe mich beim Lernen mit cabuu heute besonders angestrent.",
            "labels": {
                "1": "trifft 체berhaupt nicht zu",
                "2": "trifft eher nicht zu",
                "3": "trifft eher zu",
                "4": "trifft voll und ganz zu"
            }
        },
        {
            "id": "obstacle_initiating",
            "questionText": "Es ist mir heute schwergefallen, mit dem Lernen auf cabuu anzufangen.",
            "labels": {
                "1": "trifft 체berhaupt nicht zu",
                "2": "trifft eher nicht zu",
                "3": "trifft eher zu",
                "4": "trifft voll und ganz zu"
            }
        },
        {
            "id": "obstacle_maintaining",
            "questionText": "W채hrend ich mit cabuu gelernt habe, gab es viele Ablenkungen.",
            "labels": {
                "1": "trifft 체berhaupt nicht zu",
                "2": "trifft eher nicht zu",
                "3": "trifft eher zu",
                "4": "trifft voll und ganz zu"
            }
        }
    ]
}
