{
    "title": "Denke bei den folgenden Fragen daran, wie das Lernen mit cabuu GESTERN für dich gewesen ist.",
    "id": "evening_1",
    "questions": [
        {
            "id": "satisfaction_yesterday",
            "questionText": "Wenn ich daran denke, wie ich gestern mit cabuu gelernt habe, bin ich zufrieden mit mir.",
            "labels": {
                "1": "trifft überhaupt nicht zu",
                "2": "trifft eher nicht zu",
                "3": "trifft eher zu",
                "4": "trifft voll und ganz zu"
            }
        }
    ]
}
